memoizit/__init__.py
memoizit/memoizer.py
memoizit/storage/__init__.py
memoizit/storage/backend.py
memoizit/storage/python_backend.py
memoizit/storage/redis_backend.py
tests/__init__.py
tests/storage_test_case.py
tests/test_memoizer.py
tests/test_python_storage.py
tests/test_redis_storage.py
memoizit-1.0.0.dist-info/LICENSE
memoizit-1.0.0.dist-info/METADATA
memoizit-1.0.0.dist-info/WHEEL
memoizit-1.0.0.dist-info/top_level.txt
memoizit-1.0.0.dist-info/RECORD
