Metadata-Version: 2.1
Name: memoizit
Version: 1.0.0
Summary: A memoize library which can be used standalone, or plugged into key/value stores such as redis.     Also contains functionality to invalidate cache based on function name and arguments.
Home-page: https://github.com/blixhavn/advanced-memoize
Author: Øystein Blixhavn
Author-email: oystein@blixhavn.no
License: MIT
Project-URL: Bug Tracker, https://github.com/blixhavn/advanced-memoize/issues
Keywords: memoize,memoizing,cache,redis,memory,in-memory,invalidate
Platform: UNKNOWN
Classifier: Development Status :: 4 - Beta
Classifier: Programming Language :: Python :: 3 :: Only
Classifier: Topic :: Software Development :: Libraries
Classifier: License :: OSI Approved :: MIT License
Classifier: Operating System :: OS Independent
Classifier: Intended Audience :: Developers
Requires-Python: >=3.6
License-File: LICENSE
Provides-Extra: dev
Requires-Dist: mypy (==0.812) ; extra == 'dev'
Requires-Dist: pytest (==6.2.1) ; extra == 'dev'
Requires-Dist: pytest-cov (==2.12.1) ; extra == 'dev'
Requires-Dist: black (==21.4b0) ; extra == 'dev'
Requires-Dist: flake8 (==3.9.2) ; extra == 'dev'
Requires-Dist: redis (>=3.5.3) ; extra == 'dev'
Provides-Extra: redis
Requires-Dist: redis (>=3.5.3) ; extra == 'redis'
